CONTRIBUTING.rst
HISTORY.rst
LICENSE
MANIFEST.in
README.rst
requirements.txt
setup.cfg
setup.py
docs/Makefile
docs/authors.rst
docs/conf.py
docs/contributing.rst
docs/history.rst
docs/index.rst
docs/installation.rst
docs/make.bat
docs/readme.rst
docs/usage.rst
streamlit_theme/__init__.py
streamlit_theme/helpers.py
streamlit_theme/streamlit_theme.py
streamlit_theme.egg-info/PKG-INFO
streamlit_theme.egg-info/SOURCES.txt
streamlit_theme.egg-info/dependency_links.txt
streamlit_theme.egg-info/not-zip-safe
streamlit_theme.egg-info/requires.txt
streamlit_theme.egg-info/top_level.txt
streamlit_theme/templates/__init__.py
streamlit_theme/templates/main.css
tests/__init__.py
tests/test_streamlit_theme.py