Metadata-Version: 1.2
Name: streamlit-theme
Version: 0.58.0
Summary: Easy customisation of Streamlit look and feel.
Home-page: https://github.com/samdobson/streamlit_theme
Author: Sam Dobson
Author-email: sjd333@gmail.com
License: MIT license
Keywords: streamlit_theme
Platform: UNKNOWN
Classifier: Development Status :: 2 - Pre-Alpha
Classifier: Intended Audience :: Developers
Classifier: License :: OSI Approved :: MIT License
Classifier: Natural Language :: English
Classifier: Programming Language :: Python :: 3
Classifier: Programming Language :: Python :: 3.5
Classifier: Programming Language :: Python :: 3.6
Classifier: Programming Language :: Python :: 3.7
Classifier: Programming Language :: Python :: 3.8
Requires-Python: >=3.5
